{
  "timestamp": "2026-03-25T17:55:21.897463+00:00",
  "events": [
    {
      "subject": "tax",
      "start": "2026-03-25T05:30:00.0000000",
      "end": "2026-03-25T07:00:00.0000000",
      "attendees": [],
      "organizer": "Dave Misra",
      "location": "Microsoft Teams Meeting",
      "isAllDay": false,
      "webLink": "https://outlook.office365.com/owa/?itemid=AAMkADYwYjNmMGE4LTM4ZjYtNGI0NC1iNGJiLTk4ZWI1NmFiNzc1ZABGAAAAAACWTOM3q30fQ6AqXfuOKVI5BwAuilH2jaEmTaBeWRekOs%2B0AAAAAAENAAAuilH2jaEmTaBeWRekOs%2B0AAYQTJUFAAA%3D&exvsurl=1&path=/calendar/item"
    },
    {
      "subject": "Recurring Internal Galaxy Sync Paul/Dave/Ash/Tj",
      "start": "2026-03-25T19:00:00.0000000",
      "end": "2026-03-25T19:30:00.0000000",
      "attendees": [
        "Paul",
        "Ash",
        "Tj"
      ],
      "organizer": "Dave Misra",
      "location": "Microsoft Teams Meeting",
      "isAllDay": false,
      "webLink": "https://outlook.office365.com/owa/?itemid=AAMkADYwYjNmMGE4LTM4ZjYtNGI0NC1iNGJiLTk4ZWI1NmFiNzc1ZAFRAAgI3ooBdUFAAEYAAAAAlkzjN6t9H0OgKl37jilSOQcALopR9o2hJk2gXlkXpDrPtAAAAAABDQAALopR9o2hJk2gXlkXpDrPtAAFX9tvxAAAEA%3D%3D&exvsurl=1&path=/calendar/item"
    },
    {
      "subject": "Rescheduled Discussion JSA <> Galaxy",
      "start": "2026-03-26T14:00:00.0000000",
      "end": "2026-03-26T14:30:00.0000000",
      "attendees": [
        "France",
        "Candace",
        "Sai"
      ],
      "organizer": "France",
      "location": "Microsoft Teams Meeting",
      "isAllDay": false,
      "webLink": "https://outlook.office365.com/owa/?itemid=AAMkADYwYjNmMGE4LTM4ZjYtNGI0NC1iNGJiLTk4ZWI1NmFiNzc1ZABGAAAAAACWTOM3q30fQ6AqXfuOKVI5BwAuilH2jaEmTaBeWRekOs%2B0AAAAAAENAAAuilH2jaEmTaBeWRekOs%2B0AAYQTJUKAAA%3D&exvsurl=1&path=/calendar/item"
    },
    {
      "subject": "Nextgen <> Galaxy Intro Meeting",
      "start": "2026-03-26T15:00:00.0000000",
      "end": "2026-03-26T15:30:00.0000000",
      "attendees": [
        "hiren.parekh@nexgencloud.com",
        "Ashley"
      ],
      "organizer": "Dave Misra",
      "location": "Microsoft Teams Meeting; https://teams.microsoft.com/meet/24425599510425?p=Q1aWLs0f2RUJoS0jLj",
      "isAllDay": false,
      "webLink": "https://outlook.office365.com/owa/?itemid=AAMkADYwYjNmMGE4LTM4ZjYtNGI0NC1iNGJiLTk4ZWI1NmFiNzc1ZABGAAAAAACWTOM3q30fQ6AqXfuOKVI5BwAuilH2jaEmTaBeWRekOs%2B0AAAAAAENAAAuilH2jaEmTaBeWRekOs%2B0AAYBUbrjAAA%3D&exvsurl=1&path=/calendar/item"
    },
    {
      "subject": "Nextgen <> Galaxy Intro Meeting",
      "start": "2026-03-26T15:00:00.0000000",
      "end": "2026-03-26T15:30:00.0000000",
      "attendees": [
        "France",
        "hiren.parekh@nexgencloud.com",
        "Ashley"
      ],
      "organizer": "France",
      "location": "Microsoft Teams Meeting; https://teams.microsoft.com/meet/24425599510425?p=Q1aWLs0f2RUJoS0jLj",
      "isAllDay": false,
      "webLink": "https://outlook.office365.com/owa/?itemid=AAMkADYwYjNmMGE4LTM4ZjYtNGI0NC1iNGJiLTk4ZWI1NmFiNzc1ZABGAAAAAACWTOM3q30fQ6AqXfuOKVI5BwAuilH2jaEmTaBeWRekOs%2B0AAAAAAENAAAuilH2jaEmTaBeWRekOs%2B0AAYQTJUJAAA%3D&exvsurl=1&path=/calendar/item"
    },
    {
      "subject": "BCS/Galaxy Catch Up",
      "start": "2026-03-26T16:00:00.0000000",
      "end": "2026-03-26T16:30:00.0000000",
      "attendees": [
        "Akshay",
        "France",
        "Charlie",
        "Nick",
        "Tom"
      ],
      "organizer": "Akshay Hirani",
      "location": "Microsoft Teams Meeting",
      "isAllDay": false,
      "webLink": "https://outlook.office365.com/owa/?itemid=AAMkADYwYjNmMGE4LTM4ZjYtNGI0NC1iNGJiLTk4ZWI1NmFiNzc1ZABGAAAAAACWTOM3q30fQ6AqXfuOKVI5BwAuilH2jaEmTaBeWRekOs%2B0AAAAAAENAAAuilH2jaEmTaBeWRekOs%2B0AAXuNkl0AAA%3D&exvsurl=1&path=/calendar/item"
    },
    {
      "subject": "Redhill check in call ",
      "start": "2026-03-26T16:00:00.0000000",
      "end": "2026-03-26T16:25:00.0000000",
      "attendees": [
        "Barry",
        "Ash",
        "Paul",
        "Francis",
        "Suhaib",
        "Pelle"
      ],
      "organizer": "Barry Gross",
      "location": "Microsoft Teams Meeting",
      "isAllDay": false,
      "webLink": "https://outlook.office365.com/owa/?itemid=AAMkADYwYjNmMGE4LTM4ZjYtNGI0NC1iNGJiLTk4ZWI1NmFiNzc1ZAFRAAgI3orKn6sAAEYAAAAAlkzjN6t9H0OgKl37jilSOQcALopR9o2hJk2gXlkXpDrPtAAAAAABDQAALopR9o2hJk2gXlkXpDrPtAAD%2F9VNRAAAEA%3D%3D&exvsurl=1&path=/calendar/item"
    },
    {
      "subject": "Dave <> Research Sync",
      "start": "2026-03-26T20:30:00.0000000",
      "end": "2026-03-26T21:30:00.0000000",
      "attendees": [
        "Galaxy",
        "Ash",
        "Marcus"
      ],
      "organizer": "Galaxy Research",
      "location": "Microsoft Teams Meeting",
      "isAllDay": false,
      "webLink": "https://outlook.office365.com/owa/?itemid=AAMkADYwYjNmMGE4LTM4ZjYtNGI0NC1iNGJiLTk4ZWI1NmFiNzc1ZAFRAAgI3orKn6sAAEYAAAAAlkzjN6t9H0OgKl37jilSOQcALopR9o2hJk2gXlkXpDrPtAAAAAABDQAALopR9o2hJk2gXlkXpDrPtAAEntkB0AAAEA%3D%3D&exvsurl=1&path=/calendar/item"
    },
    {
      "subject": "SOC 2 Catch Up",
      "start": "2026-03-27T13:30:00.0000000",
      "end": "2026-03-27T14:00:00.0000000",
      "attendees": [
        "Ash",
        "Benjamin",
        "Fredy",
        "Colin",
        "Tj",
        "Paul"
      ],
      "organizer": "Ash Gupta",
      "location": "Microsoft Teams Meeting",
      "isAllDay": false,
      "webLink": "https://outlook.office365.com/owa/?itemid=AAMkADYwYjNmMGE4LTM4ZjYtNGI0NC1iNGJiLTk4ZWI1NmFiNzc1ZAFRAAgI3ouTyhTAAEYAAAAAlkzjN6t9H0OgKl37jilSOQcALopR9o2hJk2gXlkXpDrPtAAAAAABDQAALopR9o2hJk2gXlkXpDrPtAAFNe1hBAAAEA%3D%3D&exvsurl=1&path=/calendar/item"
    },
    {
      "subject": "Monday.com Review",
      "start": "2026-03-27T14:00:00.0000000",
      "end": "2026-03-27T14:30:00.0000000",
      "attendees": [
        "Paul"
      ],
      "organizer": "Paul Tester",
      "location": "Microsoft Teams Meeting",
      "isAllDay": false,
      "webLink": "https://outlook.office365.com/owa/?itemid=AAMkADYwYjNmMGE4LTM4ZjYtNGI0NC1iNGJiLTk4ZWI1NmFiNzc1ZAFRAAgI3ouTyhTAAEYAAAAAlkzjN6t9H0OgKl37jilSOQcALopR9o2hJk2gXlkXpDrPtAAAAAABDQAALopR9o2hJk2gXlkXpDrPtAAEy2UGFwAAEA%3D%3D&exvsurl=1&path=/calendar/item"
    },
    {
      "subject": "Sales Funnel Review with Ashley and Paul ",
      "start": "2026-03-27T14:30:00.0000000",
      "end": "2026-03-27T15:00:00.0000000",
      "attendees": [
        "Paul",
        "Ashley",
        "Tj"
      ],
      "organizer": "Dave Misra",
      "location": "Microsoft Teams Meeting",
      "isAllDay": false,
      "webLink": "https://outlook.office365.com/owa/?itemid=AAMkADYwYjNmMGE4LTM4ZjYtNGI0NC1iNGJiLTk4ZWI1NmFiNzc1ZAFRAAgI3ouTyhTAAEYAAAAAlkzjN6t9H0OgKl37jilSOQcALopR9o2hJk2gXlkXpDrPtAAAAAABDQAALopR9o2hJk2gXlkXpDrPtAAErJLNiwAAEA%3D%3D&exvsurl=1&path=/calendar/item"
    },
    {
      "subject": "Friday Marketing Meeting",
      "start": "2026-03-27T16:30:00.0000000",
      "end": "2026-03-27T17:00:00.0000000",
      "attendees": [
        "Sai",
        "Animesh",
        "SA"
      ],
      "organizer": "Sai Raman",
      "location": "Microsoft Teams Meeting",
      "isAllDay": false,
      "webLink": "https://outlook.office365.com/owa/?itemid=AAMkADYwYjNmMGE4LTM4ZjYtNGI0NC1iNGJiLTk4ZWI1NmFiNzc1ZAFRAAgI3ouTyhTAAEYAAAAAlkzjN6t9H0OgKl37jilSOQcALopR9o2hJk2gXlkXpDrPtAAAAAABDQAALopR9o2hJk2gXlkXpDrPtAAF3CvBFAAAEA%3D%3D&exvsurl=1&path=/calendar/item"
    }
  ]
}