{
  "timestamp": "2026-04-10T07:21:52.528356+00:00",
  "events": [
    {
      "subject": "Badminton Game with Peter ",
      "start": "2026-04-09T23:00:00.0000000",
      "end": "2026-04-10T01:00:00.0000000",
      "attendees": [],
      "organizer": "Dave Misra",
      "location": "BATTS BADMINTON TABLETENNIS SQUASH POOLTABLES FITNESS CLUB",
      "isAllDay": false,
      "webLink": "https://outlook.office365.com/owa/?itemid=AAMkADYwYjNmMGE4LTM4ZjYtNGI0NC1iNGJiLTk4ZWI1NmFiNzc1ZAFRAAgI3pXK8XOAAEYAAAAAlkzjN6t9H0OgKl37jilSOQcALopR9o2hJk2gXlkXpDrPtAAAAAABDQAALopR9o2hJk2gXlkXpDrPtAAGHmzZ9gAAEA%3D%3D&exvsurl=1&path=/calendar/item"
    },
    {
      "subject": "Shivam & Dave",
      "start": "2026-04-10T02:30:00.0000000",
      "end": "2026-04-10T03:00:00.0000000",
      "attendees": [
        "Shivam"
      ],
      "organizer": "Shivam Amati",
      "location": "Microsoft Teams Meeting",
      "isAllDay": false,
      "webLink": "https://outlook.office365.com/owa/?itemid=AAMkADYwYjNmMGE4LTM4ZjYtNGI0NC1iNGJiLTk4ZWI1NmFiNzc1ZABGAAAAAACWTOM3q30fQ6AqXfuOKVI5BwAuilH2jaEmTaBeWRekOs%2B0AAAAAAENAAAuilH2jaEmTaBeWRekOs%2B0AAY%2BjpIdAAA%3D&exvsurl=1&path=/calendar/item"
    },
    {
      "subject": "Grain / Galaxy - NWS Operating Role for Data Center Initiative",
      "start": "2026-04-10T14:00:00.0000000",
      "end": "2026-04-10T14:30:00.0000000",
      "attendees": [
        "Suraj",
        "Ricardo",
        "Paul",
        "Jeff"
      ],
      "organizer": "Suraj Aulakh",
      "location": "Microsoft Teams Meeting",
      "isAllDay": false,
      "webLink": "https://outlook.office365.com/owa/?itemid=AAMkADYwYjNmMGE4LTM4ZjYtNGI0NC1iNGJiLTk4ZWI1NmFiNzc1ZABGAAAAAACWTOM3q30fQ6AqXfuOKVI5BwAuilH2jaEmTaBeWRekOs%2B0AAAAAAENAAAuilH2jaEmTaBeWRekOs%2B0AAY%2BjpINAAA%3D&exvsurl=1&path=/calendar/item"
    },
    {
      "subject": "Sales Funnel Review with Ashley and Paul ",
      "start": "2026-04-10T14:30:00.0000000",
      "end": "2026-04-10T15:00:00.0000000",
      "attendees": [
        "Paul",
        "Ashley",
        "Tj"
      ],
      "organizer": "Dave Misra",
      "location": "Microsoft Teams Meeting",
      "isAllDay": false,
      "webLink": "https://outlook.office365.com/owa/?itemid=AAMkADYwYjNmMGE4LTM4ZjYtNGI0NC1iNGJiLTk4ZWI1NmFiNzc1ZAFRAAgI3paUG91AAEYAAAAAlkzjN6t9H0OgKl37jilSOQcALopR9o2hJk2gXlkXpDrPtAAAAAABDQAALopR9o2hJk2gXlkXpDrPtAAErJLNiwAAEA%3D%3D&exvsurl=1&path=/calendar/item"
    },
    {
      "subject": "Friday Marketing Meeting",
      "start": "2026-04-10T16:30:00.0000000",
      "end": "2026-04-10T17:00:00.0000000",
      "attendees": [
        "Sai",
        "Animesh",
        "SA",
        "Ashley"
      ],
      "organizer": "Sai Raman",
      "location": "Microsoft Teams Meeting",
      "isAllDay": false,
      "webLink": "https://outlook.office365.com/owa/?itemid=AAMkADYwYjNmMGE4LTM4ZjYtNGI0NC1iNGJiLTk4ZWI1NmFiNzc1ZAFRAAgI3paUG91AAEYAAAAAlkzjN6t9H0OgKl37jilSOQcALopR9o2hJk2gXlkXpDrPtAAAAAABDQAALopR9o2hJk2gXlkXpDrPtAAF3CvBFAAAEA%3D%3D&exvsurl=1&path=/calendar/item"
    },
    {
      "subject": "Dan <> Dave Catch Up",
      "start": "2026-04-10T18:00:00.0000000",
      "end": "2026-04-10T18:30:00.0000000",
      "attendees": [
        "France",
        "Dan"
      ],
      "organizer": "France",
      "location": "Microsoft Teams Meeting",
      "isAllDay": false,
      "webLink": "https://outlook.office365.com/owa/?itemid=AAMkADYwYjNmMGE4LTM4ZjYtNGI0NC1iNGJiLTk4ZWI1NmFiNzc1ZABGAAAAAACWTOM3q30fQ6AqXfuOKVI5BwAuilH2jaEmTaBeWRekOs%2B0AAAAAAENAAAuilH2jaEmTaBeWRekOs%2B0AAYebNn8AAA%3D&exvsurl=1&path=/calendar/item"
    }
  ]
}